aquvitae/__init__.py
aquvitae/dist.py
aquvitae/utils.py
aquvitae/algo/__init__.py
aquvitae/algo/base.py
aquvitae/algo/base_tensorflow.py
aquvitae/algo/base_torch.py
aquvitae/algo/st_tensorflow.py
aquvitae/algo/st_torch.py
aquvitae-0.1.7.dist-info/LICENSE
aquvitae-0.1.7.dist-info/METADATA
aquvitae-0.1.7.dist-info/WHEEL
aquvitae-0.1.7.dist-info/top_level.txt
aquvitae-0.1.7.dist-info/RECORD
